[
  {
    "value": 24.4,
    "unitId": 23,
    "typeId": 2,
    "sensorId": 11810,
    "categoryId": 3,
    "category": "Temperature",
    "type": "Device Temperature",
    "unit": "°C",
    "stationId": 5438,
    "deviceId": 13574,
    "timestamp": "2026-05-29T02:00:04.001Z",
    "sequence": 1
  },
  {
    "value": 24.1,
    "unitId": 23,
    "typeId": 2,
    "sensorId": 11810,
    "categoryId": 3,
    "category": "Temperature",
    "type": "Device Temperature",
    "unit": "°C",
    "stationId": 5438,
    "deviceId": 13574,
    "timestamp": "2026-05-28T14:00:23.001Z",
    "sequence": 1
  },
  {
    "value": 24.5,
    "unitId": 23,
    "typeId": 2,
    "sensorId": 11810,
    "categoryId": 3,
    "category": "Temperature",
    "type": "Device Temperature",
    "unit": "°C",
    "stationId": 5438,
    "deviceId": 13574,
    "timestamp": "2026-05-28T08:00:22.001Z",
    "sequence": 1
  },
  {
    "value": 25,
    "unitId": 23,
    "typeId": 2,
    "sensorId": 11810,
    "categoryId": 3,
    "category": "Temperature",
    "type": "Device Temperature",
    "unit": "°C",
    "stationId": 5438,
    "deviceId": 13574,
    "timestamp": "2026-05-28T02:00:04.001Z",
    "sequence": 1
  },
  {
    "value": 22.3,
    "unitId": 23,
    "typeId": 2,
    "sensorId": 11810,
    "categoryId": 3,
    "category": "Temperature",
    "type": "Device Temperature",
    "unit": "°C",
    "stationId": 5438,
    "deviceId": 13574,
    "timestamp": "2026-05-27T14:00:23.001Z",
    "sequence": 1
  },
  {
    "value": 22.5,
    "unitId": 23,
    "typeId": 2,
    "sensorId": 11810,
    "categoryId": 3,
    "category": "Temperature",
    "type": "Device Temperature",
    "unit": "°C",
    "stationId": 5438,
    "deviceId": 13574,
    "timestamp": "2026-05-27T11:00:22.001Z",
    "sequence": 1
  },
  {
    "value": 22.6,
    "unitId": 23,
    "typeId": 2,
    "sensorId": 11810,
    "categoryId": 3,
    "category": "Temperature",
    "type": "Device Temperature",
    "unit": "°C",
    "stationId": 5438,
    "deviceId": 13574,
    "timestamp": "2026-05-27T08:00:23.001Z",
    "sequence": 1
  },
  {
    "value": 21.5,
    "unitId": 23,
    "typeId": 2,
    "sensorId": 11810,
    "categoryId": 3,
    "category": "Temperature",
    "type": "Device Temperature",
    "unit": "°C",
    "stationId": 5438,
    "deviceId": 13574,
    "timestamp": "2026-05-27T02:00:04.001Z",
    "sequence": 1
  },
  {
    "value": 21.9,
    "unitId": 23,
    "typeId": 2,
    "sensorId": 11810,
    "categoryId": 3,
    "category": "Temperature",
    "type": "Device Temperature",
    "unit": "°C",
    "stationId": 5438,
    "deviceId": 13574,
    "timestamp": "2026-05-26T14:00:22.001Z",
    "sequence": 1
  },
  {
    "value": 21.8,
    "unitId": 23,
    "typeId": 2,
    "sensorId": 11810,
    "categoryId": 3,
    "category": "Temperature",
    "type": "Device Temperature",
    "unit": "°C",
    "stationId": 5438,
    "deviceId": 13574,
    "timestamp": "2026-05-26T11:00:23.001Z",
    "sequence": 1
  },
  {
    "value": 21.7,
    "unitId": 23,
    "typeId": 2,
    "sensorId": 11810,
    "categoryId": 3,
    "category": "Temperature",
    "type": "Device Temperature",
    "unit": "°C",
    "stationId": 5438,
    "deviceId": 13574,
    "timestamp": "2026-05-26T08:00:23.001Z",
    "sequence": 1
  },
  {
    "value": 21.8,
    "unitId": 23,
    "typeId": 2,
    "sensorId": 11810,
    "categoryId": 3,
    "category": "Temperature",
    "type": "Device Temperature",
    "unit": "°C",
    "stationId": 5438,
    "deviceId": 13574,
    "timestamp": "2026-05-26T02:00:04.001Z",
    "sequence": 1
  },
  {
    "value": 22.4,
    "unitId": 23,
    "typeId": 2,
    "sensorId": 11810,
    "categoryId": 3,
    "category": "Temperature",
    "type": "Device Temperature",
    "unit": "°C",
    "stationId": 5438,
    "deviceId": 13574,
    "timestamp": "2026-05-25T14:00:23.001Z",
    "sequence": 1
  },
  {
    "value": 22.4,
    "unitId": 23,
    "typeId": 2,
    "sensorId": 11810,
    "categoryId": 3,
    "category": "Temperature",
    "type": "Device Temperature",
    "unit": "°C",
    "stationId": 5438,
    "deviceId": 13574,
    "timestamp": "2026-05-25T11:00:22.001Z",
    "sequence": 1
  },
  {
    "value": 22.3,
    "unitId": 23,
    "typeId": 2,
    "sensorId": 11810,
    "categoryId": 3,
    "category": "Temperature",
    "type": "Device Temperature",
    "unit": "°C",
    "stationId": 5438,
    "deviceId": 13574,
    "timestamp": "2026-05-25T08:00:22.001Z",
    "sequence": 1
  },
  {
    "value": 22.5,
    "unitId": 23,
    "typeId": 2,
    "sensorId": 11810,
    "categoryId": 3,
    "category": "Temperature",
    "type": "Device Temperature",
    "unit": "°C",
    "stationId": 5438,
    "deviceId": 13574,
    "timestamp": "2026-05-25T02:00:09.001Z",
    "sequence": 1
  },
  {
    "value": 23,
    "unitId": 23,
    "typeId": 2,
    "sensorId": 11810,
    "categoryId": 3,
    "category": "Temperature",
    "type": "Device Temperature",
    "unit": "°C",
    "stationId": 5438,
    "deviceId": 13574,
    "timestamp": "2026-05-24T14:00:22.001Z",
    "sequence": 1
  },
  {
    "value": 23.1,
    "unitId": 23,
    "typeId": 2,
    "sensorId": 11810,
    "categoryId": 3,
    "category": "Temperature",
    "type": "Device Temperature",
    "unit": "°C",
    "stationId": 5438,
    "deviceId": 13574,
    "timestamp": "2026-05-24T11:00:23.001Z",
    "sequence": 1
  },
  {
    "value": 23.6,
    "unitId": 23,
    "typeId": 2,
    "sensorId": 11810,
    "categoryId": 3,
    "category": "Temperature",
    "type": "Device Temperature",
    "unit": "°C",
    "stationId": 5438,
    "deviceId": 13574,
    "timestamp": "2026-05-24T08:00:22.001Z",
    "sequence": 1
  },
  {
    "value": 22.8,
    "unitId": 23,
    "typeId": 2,
    "sensorId": 11810,
    "categoryId": 3,
    "category": "Temperature",
    "type": "Device Temperature",
    "unit": "°C",
    "stationId": 5438,
    "deviceId": 13574,
    "timestamp": "2026-05-24T02:00:04.001Z",
    "sequence": 1
  },
  {
    "value": 23.3,
    "unitId": 23,
    "typeId": 2,
    "sensorId": 11810,
    "categoryId": 3,
    "category": "Temperature",
    "type": "Device Temperature",
    "unit": "°C",
    "stationId": 5438,
    "deviceId": 13574,
    "timestamp": "2026-05-23T14:00:23.001Z",
    "sequence": 1
  },
  {
    "value": 22.6,
    "unitId": 23,
    "typeId": 2,
    "sensorId": 11810,
    "categoryId": 3,
    "category": "Temperature",
    "type": "Device Temperature",
    "unit": "°C",
    "stationId": 5438,
    "deviceId": 13574,
    "timestamp": "2026-05-23T11:00:23.001Z",
    "sequence": 1
  },
  {
    "value": 22.6,
    "unitId": 23,
    "typeId": 2,
    "sensorId": 11810,
    "categoryId": 3,
    "category": "Temperature",
    "type": "Device Temperature",
    "unit": "°C",
    "stationId": 5438,
    "deviceId": 13574,
    "timestamp": "2026-05-23T08:00:23.001Z",
    "sequence": 1
  },
  {
    "value": 22.2,
    "unitId": 23,
    "typeId": 2,
    "sensorId": 11810,
    "categoryId": 3,
    "category": "Temperature",
    "type": "Device Temperature",
    "unit": "°C",
    "stationId": 5438,
    "deviceId": 13574,
    "timestamp": "2026-05-23T02:00:04.001Z",
    "sequence": 1
  },
  {
    "value": 22.8,
    "unitId": 23,
    "typeId": 2,
    "sensorId": 11810,
    "categoryId": 3,
    "category": "Temperature",
    "type": "Device Temperature",
    "unit": "°C",
    "stationId": 5438,
    "deviceId": 13574,
    "timestamp": "2026-05-22T14:00:22.001Z",
    "sequence": 1
  },
  {
    "value": 22.6,
    "unitId": 23,
    "typeId": 2,
    "sensorId": 11810,
    "categoryId": 3,
    "category": "Temperature",
    "type": "Device Temperature",
    "unit": "°C",
    "stationId": 5438,
    "deviceId": 13574,
    "timestamp": "2026-05-22T11:00:22.001Z",
    "sequence": 1
  }
]